setup.py
dsndls_distributions/Binomialdistribution.py
dsndls_distributions/Gaussiandistribution.py
dsndls_distributions/Generaldistribution.py
dsndls_distributions/__init__.py
dsndls_distributions.egg-info/PKG-INFO
dsndls_distributions.egg-info/SOURCES.txt
dsndls_distributions.egg-info/dependency_links.txt
dsndls_distributions.egg-info/not-zip-safe
dsndls_distributions.egg-info/top_level.txt