Metadata-Version: 1.0
Name: dsndls-distributions
Version: 0.1
Summary: Gaussian and Binomial distributions
Home-page: UNKNOWN
Author: Liberto Siahaan
Author-email: UNKNOWN
License: UNKNOWN
Platform: UNKNOWN
